arcade_hubspot_cms_api/__init__.py
arcade_hubspot_cms_api/moar/hubspot_cms.json
arcade_hubspot_cms_api/moar/openapi.json
arcade_hubspot_cms_api/tools/__init__.py
arcade_hubspot_cms_api/tools/request_body_schemas.py
arcade_hubspot_cms_api/wrapper_tools/AddHubdbTableRow.json
arcade_hubspot_cms_api/wrapper_tools/ArchiveBlogTags.json
arcade_hubspot_cms_api/wrapper_tools/ArchiveHubdbTable.json
arcade_hubspot_cms_api/wrapper_tools/AttachAuthorToMultilangGroup.json
arcade_hubspot_cms_api/wrapper_tools/AttachBlogPostToLanguageGroup.json
arcade_hubspot_cms_api/wrapper_tools/AttachBlogToLanguageGroup.json
arcade_hubspot_cms_api/wrapper_tools/AttachLandingPageToLanguageGroup.json
arcade_hubspot_cms_api/wrapper_tools/AttachPageToLanguageGroup.json
arcade_hubspot_cms_api/wrapper_tools/AttachTagToLanguageGroup.json
arcade_hubspot_cms_api/wrapper_tools/BatchUpdateTableRowsHubspot.json
arcade_hubspot_cms_api/wrapper_tools/CheckExtractionStatus.json
arcade_hubspot_cms_api/wrapper_tools/CloneBlogPost.json
arcade_hubspot_cms_api/wrapper_tools/CloneDraftTableRowsHubspot.json
arcade_hubspot_cms_api/wrapper_tools/CloneHubdbDraftRow.json
arcade_hubspot_cms_api/wrapper_tools/CloneHubdbTable.json
arcade_hubspot_cms_api/wrapper_tools/CloneLandingPageHubspot.json
arcade_hubspot_cms_api/wrapper_tools/CloneSitePage.json
arcade_hubspot_cms_api/wrapper_tools/CreateAbTestVariation.json
arcade_hubspot_cms_api/wrapper_tools/CreateAttentionSpanEvent.json
arcade_hubspot_cms_api/wrapper_tools/CreateBatchBlogPosts.json
arcade_hubspot_cms_api/wrapper_tools/CreateBlogAuthor.json
arcade_hubspot_cms_api/wrapper_tools/CreateBlogAuthorLanguageVariation.json
arcade_hubspot_cms_api/wrapper_tools/CreateBlogAuthorsBatch.json
arcade_hubspot_cms_api/wrapper_tools/CreateBlogLanguageVariation.json
arcade_hubspot_cms_api/wrapper_tools/CreateBlogPost.json
arcade_hubspot_cms_api/wrapper_tools/CreateBlogTag.json
arcade_hubspot_cms_api/wrapper_tools/CreateBlogTagLanguageVariation.json
arcade_hubspot_cms_api-1.0.0.dist-info/METADATA
arcade_hubspot_cms_api-1.0.0.dist-info/WHEEL
arcade_hubspot_cms_api-1.0.0.dist-info/entry_points.txt
arcade_hubspot_cms_api-1.0.0.dist-info/licenses/LICENSE
arcade_hubspot_cms_api-1.0.0.dist-info/RECORD
